{"clt_coupon": 387, "clt_coupon_comment": 64, "clt_coupon_order": 1060618, "clt_coupon_order_action": 3880980, "clt_coupon_order_goods": 1060617, "clt_coupon_sequence": 387, "clt_coupon_untying_log": 11, "clt_discount_class": 79, "clt_discount_news": 4, "clt_discount_news_class": 1, "clt_discount_public": 1, "clt_discount_services": 3, "clt_eb_combination": 215, "clt_eb_combination_delivery": 87, "clt_eb_combination_draft": 0, "clt_eb_commissioner": 1021, "clt_eb_commissioner_leader": 57, "clt_eb_express": 28, "clt_eb_goods_search": 11, "clt_eb_group_colonel": 667602, "clt_eb_group_colonel_income": 20843, "clt_eb_group_colonel_record": 196, "clt_eb_group_colonel_verify": 392, "clt_eb_group_colonel_withdraw": 1287, "clt_eb_houniao_order": 31, "clt_eb_live_room": 2, "clt_eb_live_subscribe": 639, "clt_eb_order_export": 26075, "clt_eb_order_refund": 1055, "clt_eb_region": 704724, "clt_eb_selection": 16, "clt_eb_shipping_delivery": 162, "clt_eb_shipping_delivery_product": 2393, "clt_eb_shipping_driver": 36, "clt_eb_shipping_templates": 90, "clt_eb_shipping_templates_free": 0, "clt_eb_shipping_templates_region": 22917, "clt_eb_spread_wechat": 360, "clt_eb_store_cart": 33724, "clt_eb_store_cate": 36, "clt_eb_store_category": 165, "clt_eb_store_combination": 5381, "clt_eb_store_coupon_issue": 0, "clt_eb_store_coupon_issue_user": 0, "clt_eb_store_order": 65300, "clt_eb_store_order_cart_info": 0, "clt_eb_store_order_logistics": 0, "clt_eb_store_order_status": 0, "clt_eb_store_pic": 0, "clt_eb_store_product": 0, "clt_eb_store_product_attr": 0, "clt_eb_store_product_attr_result": 0, "clt_eb_store_product_attr_value": 0, "clt_eb_store_product_cate": 0, "clt_eb_store_product_coupon": 0, "clt_eb_store_product_description": 0, "clt_eb_store_product_recommend": 0, "clt_eb_store_product_relation": 0, "clt_eb_store_product_rule": 0, "clt_eb_store_product_stock_log": 0, "clt_eb_store_visit": 0, "clt_eb_sub_message": 0, "clt_eb_supplier": 0, "clt_eb_supplier_address": 0, "clt_eb_supplier_income": 0, "clt_eb_supplier_record": 0, "clt_eb_system_admin": 0, "clt_eb_system_area": 0, "clt_eb_system_area_income": 0, "clt_eb_system_attachment": 0, "clt_eb_system_attachment_category": 0, "clt_eb_system_city": 0, "clt_eb_system_config": 0, "clt_eb_system_config_tab": 0, "clt_eb_system_group": 0, "clt_eb_system_group_data": 0, "clt_eb_system_log": 0, "clt_eb_system_menus": 0, "clt_eb_system_role": 0, "clt_eb_system_store": 0, "clt_eb_take_order_record": 0, "clt_eb_template_message": 0, "clt_eb_tuan_user": 0, "clt_eb_tuan_user_address": 0, "clt_eb_tuan_user_expire": 0, "clt_eb_tuan_user_inside": 0, "clt_eb_tuan_user_place": 0, "clt_eb_tuan_user_wechat": 0, "clt_eb_user_field": 0, "clt_eb_user_subscribe": 0, "clt_eb_village_information": 0, "clt_eb_village_introduce": 0, "clt_eb_village_message": 0, "clt_eb_village_photo": 0, "clt_eb_wechat_icon": 0, "clt_eb_wechat_menu": 0, "clt_eb_work_group": 0, "clt_eb_work_group_user": 0, "clt_gift_card": 0, "clt_order_refund": 0, "clt_pop_shop_code": 0, "clt_pop_shop_data": 0, "clt_supplier": 0, "clt_supplier_chain": 0, "clt_supplier_draft": 0, "clt_supplier_product": 0, "clt_supplier_product_action": 0, "clt_trade_area": 0, "clt_wechat_group": 0, "clt_work_anchor": 0, "clt_work_user": 0}